[
    {
        "titre": "cuisine du monde",
        "description": "test",
        "date_debut": "2020-12-16",
        "heure_debut": "11:54",
        "nombre_places": "7",
        "duree": "3",
        "prix": "100",
        "image": "",
        "id": "b256170c9d7048cb3d178e4f240df5b4",
        "proprietaire": 1,
        "date_ajout": [
            1607925274,
            "2020-12-14"
        ],
        "etat_atelier": "D\u00e9sactiv\u00e9",
        "participants": [],
        "modifie": false
    },
    {
        "titre": "cuisine du monde",
        "description": "Specialiqmdkjfhqsmflkjghqw",
        "date_debut": "2020-12-16",
        "heure_debut": "09:57",
        "nombre_places": "3",
        "duree": "3",
        "prix": "4",
        "image": "",
        "id": "4003d2b1b82a015f61c56a68e18d5834",
        "proprietaire": 1,
        "date_ajout": [
            1607921868,
            "2020-12-14"
        ],
        "etat_atelier": "Active",
        "participants": [],
        "modifie": false
    }
]